llmux/__init__.py
llmux/api.py
llmux/evaluator.py
llmux/provider.py
llmux/selector.py
llmux_optimizer-0.1.0.dist-info/licenses/LICENSE
llmux_optimizer-0.1.0.dist-info/METADATA
llmux_optimizer-0.1.0.dist-info/WHEEL
llmux_optimizer-0.1.0.dist-info/top_level.txt
llmux_optimizer-0.1.0.dist-info/RECORD
