Metadata-Version: 2.4
Name: llmux-optimizer
Version: 0.1.0
Summary: Automatically find cheaper LLM alternatives while maintaining performance
Home-page: https://github.com/mihirahuja/llmux
Author: Mihir Ahuja
Author-email: Mihir Ahuja <mihirahuja09@gmail.com>
License: MIT
Project-URL: Homepage, https://github.com/mihirahuja/llmux
Project-URL: Documentation, https://github.com/mihirahuja/llmux#readme
Project-URL: Repository, https://github.com/mihirahuja/llmux
Project-URL: Issues, https://github.com/mihirahuja/llmux/issues
Keywords: llm,ai,cost-optimization,machine-learning,openai,anthropic
Classifier: Development Status :: 4 - Beta
Classifier: Intended Audience :: Developers
Classifier: License :: OSI Approved :: MIT License
Classifier: Programming Language :: Python :: 3
Classifier: Programming Language :: Python :: 3.8
Classifier: Programming Language :: Python :: 3.9
Classifier: Programming Language :: Python :: 3.10
Classifier: Programming Language :: Python :: 3.11
Classifier: Programming Language :: Python :: 3.12
Classifier: Topic :: Scientific/Engineering :: Artificial Intelligence
Classifier: Topic :: Software Development :: Libraries :: Python Modules
Requires-Python: >=3.8
License-File: LICENSE
Requires-Dist: requests>=2.25.0
Requires-Dist: tqdm>=4.60.0
Requires-Dist: openai>=1.0.0
Requires-Dist: anthropic>=0.5.0
Provides-Extra: dev
Requires-Dist: pytest>=6.0; extra == "dev"
Requires-Dist: black; extra == "dev"
Requires-Dist: flake8; extra == "dev"
Requires-Dist: mypy; extra == "dev"
Requires-Dist: isort; extra == "dev"
Provides-Extra: data
Requires-Dist: pandas>=1.3.0; extra == "data"
Requires-Dist: datasets>=2.0.0; extra == "data"
Dynamic: author
Dynamic: home-page
Dynamic: license-file
Dynamic: requires-python
